PC.vhd
-------------------------------------------------------------------------------
-- Title      : PC Logic
-- Project    : 
-------------------------------------------------------------------------------
-- File       : PC.vhd
-- Author     : Nixon Ortiz
-- Company    : MAELPRO
-- Created    : 
-- Last update: 
-- Platform   : 
-- Standard   : VHDL
-- Description: It references to the first byte of an instruction in the IMem
--              so the PC always increment in +4. 
--              When reset, PC points to Zero
-------------------------------------------------------------------------------
library ieee;
use ieee.std_logic_1164.all;
use ieee.numeric_std.all;

entity PC_logic is
    port (
        clk : in std_logic;
        rst : in std_logic;
        pc  : out std_logic_vector(31 downto 0)
    );
end PC_logic;

architecture rtl of PC_logic is
    signal pc_next : unsigned(31 downto 0);
    signal pc_reg : unsigned(31 downto 0);
begin

    --Sequential logic on PC
    process(clk,rst)
    begin
        if(rst='1')then
            pc_reg  <=  (others=>'0');
        elsif(rising_edge(clk))then
            pc_reg <= pc_next;
        end if; 
    end process;


    pc_next <= pc_reg + "100";

    pc <= std_logic_vector(pc_reg);

end architecture;

pc_tb.vhd
library ieee;
use ieee.std_logic_1164.all;
use ieee.numeric_std.all;

use std.textio.all;
-- use std.env.finish;

entity PC_logic_tb is
end PC_logic_tb;

architecture sim of PC_logic_tb is

    constant clk_hz : integer := 100e6;
    constant clk_period : time := 1 sec / clk_hz;

    signal clk : std_logic := '1';
    signal rst : std_logic := '1';
    signal pc_s : std_logic_vector(31 downto 0);

begin

    clk <= not clk after clk_period / 2;

    DUT : entity work.PC_logic(rtl)
    port map (
        clk => clk,
        rst => rst,
        pc => pc_s
    );

    SEQUENCER_PROC : process
    begin
        wait for clk_period * 2;

        rst <= '1';

        wait for clk_period * 2;

        rst <= '0';

        wait for clk_period * 100;
        assert false
            report "Replace this with your test cases"
            severity failure;
    end process;

end architecture;

PC_logic_tb.vcd
$date
  Thu Feb 16 14:03:37 2023
$end
$version
  GHDL v0
$end
$timescale
  1 fs
$end
$scope module standard $end
$upscope $end
$scope module std_logic_1164 $end
$upscope $end
$scope module numeric_std $end
$upscope $end
$scope module textio $end
$upscope $end
$scope module pc_logic_tb $end
$var reg 1 ! clk $end
$var reg 1 " rst $end
$var reg 32 # pc_s[31:0] $end
$scope module dut $end
$var reg 1 $ clk $end
$var reg 1 % rst $end
$var reg 32 & pc[31:0] $end
$var reg 32 ' pc_next[31:0] $end
$var reg 32 ( pc_reg[31:0] $end
$upscope $end
$upscope $end
$enddefinitions $end
#0
1!
1"
b00000000000000000000000000000000 #
1$
1%
b00000000000000000000000000000000 &
b00000000000000000000000000000100 '
b00000000000000000000000000000000 (
#5000000
0!
0$
#10000000
1!
1$
#15000000
0!
0$
#20000000
1!
1$
#25000000
0!
0$
#30000000
1!
1$
#35000000
0!
0$
#40000000
1!
0"
1$
0%
#45000000
0!
0$
#50000000
1!
b00000000000000000000000000000100 #
1$
b00000000000000000000000000000100 &
b00000000000000000000000000001000 '
b00000000000000000000000000000100 (
#55000000
0!
0$
#60000000
1!
b00000000000000000000000000001000 #
1$
b00000000000000000000000000001000 &
b00000000000000000000000000001100 '
b00000000000000000000000000001000 (
#65000000
0!
0$
#70000000
1!
b00000000000000000000000000001100 #
1$
b00000000000000000000000000001100 &
b00000000000000000000000000010000 '
b00000000000000000000000000001100 (
#75000000
0!
0$
#80000000
1!
b00000000000000000000000000010000 #
1$
b00000000000000000000000000010000 &
b00000000000000000000000000010100 '
b00000000000000000000000000010000 (
#85000000
0!
0$
#90000000
1!
b00000000000000000000000000010100 #
1$
b00000000000000000000000000010100 &
b00000000000000000000000000011000 '
b00000000000000000000000000010100 (
#95000000
0!
0$
#100000000
1!
b00000000000000000000000000011000 #
1$
b00000000000000000000000000011000 &
b00000000000000000000000000011100 '
b00000000000000000000000000011000 (
#105000000
0!
0$
#110000000
1!
b00000000000000000000000000011100 #
1$
b00000000000000000000000000011100 &
b00000000000000000000000000100000 '
b00000000000000000000000000011100 (
#115000000
0!
0$
#120000000
1!
b00000000000000000000000000100000 #
1$
b00000000000000000000000000100000 &
b00000000000000000000000000100100 '
b00000000000000000000000000100000 (
#125000000
0!
0$
#130000000
1!
b00000000000000000000000000100100 #
1$
b00000000000000000000000000100100 &
b00000000000000000000000000101000 '
b00000000000000000000000000100100 (
#135000000
0!
0$
#140000000
1!
b00000000000000000000000000101000 #
1$
b00000000000000000000000000101000 &
b00000000000000000000000000101100 '
b00000000000000000000000000101000 (
#145000000
0!
0$
#150000000
1!
b00000000000000000000000000101100 #
1$
b00000000000000000000000000101100 &
b00000000000000000000000000110000 '
b00000000000000000000000000101100 (
#155000000
0!
0$
#160000000
1!
b00000000000000000000000000110000 #
1$
b00000000000000000000000000110000 &
b00000000000000000000000000110100 '
b00000000000000000000000000110000 (
#165000000
0!
0$
#170000000
1!
b00000000000000000000000000110100 #
1$
b00000000000000000000000000110100 &
b00000000000000000000000000111000 '
b00000000000000000000000000110100 (
#175000000
0!
0$
#180000000
1!
b00000000000000000000000000111000 #
1$
b00000000000000000000000000111000 &
b00000000000000000000000000111100 '
b00000000000000000000000000111000 (
#185000000
0!
0$
#190000000
1!
b00000000000000000000000000111100 #
1$
b00000000000000000000000000111100 &
b00000000000000000000000001000000 '
b00000000000000000000000000111100 (
#195000000
0!
0$
#200000000
1!
b00000000000000000000000001000000 #
1$
b00000000000000000000000001000000 &
b00000000000000000000000001000100 '
b00000000000000000000000001000000 (
#205000000
0!
0$
#210000000
1!
b00000000000000000000000001000100 #
1$
b00000000000000000000000001000100 &
b00000000000000000000000001001000 '
b00000000000000000000000001000100 (
#215000000
0!
0$
#220000000
1!
b00000000000000000000000001001000 #
1$
b00000000000000000000000001001000 &
b00000000000000000000000001001100 '
b00000000000000000000000001001000 (
#225000000
0!
0$
#230000000
1!
b00000000000000000000000001001100 #
1$
b00000000000000000000000001001100 &
b00000000000000000000000001010000 '
b00000000000000000000000001001100 (
#235000000
0!
0$
#240000000
1!
b00000000000000000000000001010000 #
1$
b00000000000000000000000001010000 &
b00000000000000000000000001010100 '
b00000000000000000000000001010000 (
#245000000
0!
0$
#250000000
1!
b00000000000000000000000001010100 #
1$
b00000000000000000000000001010100 &
b00000000000000000000000001011000 '
b00000000000000000000000001010100 (
#255000000
0!
0$
#260000000
1!
b00000000000000000000000001011000 #
1$
b00000000000000000000000001011000 &
b00000000000000000000000001011100 '
b00000000000000000000000001011000 (
#265000000
0!
0$
#270000000
1!
b00000000000000000000000001011100 #
1$
b00000000000000000000000001011100 &
b00000000000000000000000001100000 '
b00000000000000000000000001011100 (
#275000000
0!
0$
#280000000
1!
b00000000000000000000000001100000 #
1$
b00000000000000000000000001100000 &
b00000000000000000000000001100100 '
b00000000000000000000000001100000 (
#285000000
0!
0$
#290000000
1!
b00000000000000000000000001100100 #
1$
b00000000000000000000000001100100 &
b00000000000000000000000001101000 '
b00000000000000000000000001100100 (
#295000000
0!
0$
#300000000
1!
b00000000000000000000000001101000 #
1$
b00000000000000000000000001101000 &
b00000000000000000000000001101100 '
b00000000000000000000000001101000 (
#305000000
0!
0$
#310000000
1!
b00000000000000000000000001101100 #
1$
b00000000000000000000000001101100 &
b00000000000000000000000001110000 '
b00000000000000000000000001101100 (
#315000000
0!
0$
#320000000
1!
b00000000000000000000000001110000 #
1$
b00000000000000000000000001110000 &
b00000000000000000000000001110100 '
b00000000000000000000000001110000 (
#325000000
0!
0$
#330000000
1!
b00000000000000000000000001110100 #
1$
b00000000000000000000000001110100 &
b00000000000000000000000001111000 '
b00000000000000000000000001110100 (
#335000000
0!
0$
#340000000
1!
b00000000000000000000000001111000 #
1$
b00000000000000000000000001111000 &
b00000000000000000000000001111100 '
b00000000000000000000000001111000 (
#345000000
0!
0$
#350000000
1!
b00000000000000000000000001111100 #
1$
b00000000000000000000000001111100 &
b00000000000000000000000010000000 '
b00000000000000000000000001111100 (
#355000000
0!
0$
#360000000
1!
b00000000000000000000000010000000 #
1$
b00000000000000000000000010000000 &
b00000000000000000000000010000100 '
b00000000000000000000000010000000 (
#365000000
0!
0$
#370000000
1!
b00000000000000000000000010000100 #
1$
b00000000000000000000000010000100 &
b00000000000000000000000010001000 '
b00000000000000000000000010000100 (
#375000000
0!
0$
#380000000
1!
b00000000000000000000000010001000 #
1$
b00000000000000000000000010001000 &
b00000000000000000000000010001100 '
b00000000000000000000000010001000 (
#385000000
0!
0$
#390000000
1!
b00000000000000000000000010001100 #
1$
b00000000000000000000000010001100 &
b00000000000000000000000010010000 '
b00000000000000000000000010001100 (
#395000000
0!
0$
#400000000
1!
b00000000000000000000000010010000 #
1$
b00000000000000000000000010010000 &
b00000000000000000000000010010100 '
b00000000000000000000000010010000 (
#405000000
0!
0$
#410000000
1!
b00000000000000000000000010010100 #
1$
b00000000000000000000000010010100 &
b00000000000000000000000010011000 '
b00000000000000000000000010010100 (
#415000000
0!
0$
#420000000
1!
b00000000000000000000000010011000 #
1$
b00000000000000000000000010011000 &
b00000000000000000000000010011100 '
b00000000000000000000000010011000 (
#425000000
0!
0$
#430000000
1!
b00000000000000000000000010011100 #
1$
b00000000000000000000000010011100 &
b00000000000000000000000010100000 '
b00000000000000000000000010011100 (
#435000000
0!
0$
#440000000
1!
b00000000000000000000000010100000 #
1$
b00000000000000000000000010100000 &
b00000000000000000000000010100100 '
b00000000000000000000000010100000 (
#445000000
0!
0$
#450000000
1!
b00000000000000000000000010100100 #
1$
b00000000000000000000000010100100 &
b00000000000000000000000010101000 '
b00000000000000000000000010100100 (
#455000000
0!
0$
#460000000
1!
b00000000000000000000000010101000 #
1$
b00000000000000000000000010101000 &
b00000000000000000000000010101100 '
b00000000000000000000000010101000 (
#465000000
0!
0$
#470000000
1!
b00000000000000000000000010101100 #
1$
b00000000000000000000000010101100 &
b00000000000000000000000010110000 '
b00000000000000000000000010101100 (
#475000000
0!
0$
#480000000
1!
b00000000000000000000000010110000 #
1$
b00000000000000000000000010110000 &
b00000000000000000000000010110100 '
b00000000000000000000000010110000 (
#485000000
0!
0$
#490000000
1!
b00000000000000000000000010110100 #
1$
b00000000000000000000000010110100 &
b00000000000000000000000010111000 '
b00000000000000000000000010110100 (
#495000000
0!
0$
#500000000
1!
b00000000000000000000000010111000 #
1$
b00000000000000000000000010111000 &
b00000000000000000000000010111100 '
b00000000000000000000000010111000 (
#505000000
0!
0$
#510000000
1!
b00000000000000000000000010111100 #
1$
b00000000000000000000000010111100 &
b00000000000000000000000011000000 '
b00000000000000000000000010111100 (
#515000000
0!
0$
#520000000
1!
b00000000000000000000000011000000 #
1$
b00000000000000000000000011000000 &
b00000000000000000000000011000100 '
b00000000000000000000000011000000 (
#525000000
0!
0$
#530000000
1!
b00000000000000000000000011000100 #
1$
b00000000000000000000000011000100 &
b00000000000000000000000011001000 '
b00000000000000000000000011000100 (
#535000000
0!
0$
#540000000
1!
b00000000000000000000000011001000 #
1$
b00000000000000000000000011001000 &
b00000000000000000000000011001100 '
b00000000000000000000000011001000 (
#545000000
0!
0$
#550000000
1!
b00000000000000000000000011001100 #
1$
b00000000000000000000000011001100 &
b00000000000000000000000011010000 '
b00000000000000000000000011001100 (
#555000000
0!
0$
#560000000
1!
b00000000000000000000000011010000 #
1$
b00000000000000000000000011010000 &
b00000000000000000000000011010100 '
b00000000000000000000000011010000 (
#565000000
0!
0$
#570000000
1!
b00000000000000000000000011010100 #
1$
b00000000000000000000000011010100 &
b00000000000000000000000011011000 '
b00000000000000000000000011010100 (
#575000000
0!
0$
#580000000
1!
b00000000000000000000000011011000 #
1$
b00000000000000000000000011011000 &
b00000000000000000000000011011100 '
b00000000000000000000000011011000 (
#585000000
0!
0$
#590000000
1!
b00000000000000000000000011011100 #
1$
b00000000000000000000000011011100 &
b00000000000000000000000011100000 '
b00000000000000000000000011011100 (
#595000000
0!
0$
#600000000
1!
b00000000000000000000000011100000 #
1$
b00000000000000000000000011100000 &
b00000000000000000000000011100100 '
b00000000000000000000000011100000 (
#605000000
0!
0$
#610000000
1!
b00000000000000000000000011100100 #
1$
b00000000000000000000000011100100 &
b00000000000000000000000011101000 '
b00000000000000000000000011100100 (
#615000000
0!
0$
#620000000
1!
b00000000000000000000000011101000 #
1$
b00000000000000000000000011101000 &
b00000000000000000000000011101100 '
b00000000000000000000000011101000 (
#625000000
0!
0$
#630000000
1!
b00000000000000000000000011101100 #
1$
b00000000000000000000000011101100 &
b00000000000000000000000011110000 '
b00000000000000000000000011101100 (
#635000000
0!
0$
#640000000
1!
b00000000000000000000000011110000 #
1$
b00000000000000000000000011110000 &
b00000000000000000000000011110100 '
b00000000000000000000000011110000 (
#645000000
0!
0$
#650000000
1!
b00000000000000000000000011110100 #
1$
b00000000000000000000000011110100 &
b00000000000000000000000011111000 '
b00000000000000000000000011110100 (
#655000000
0!
0$
#660000000
1!
b00000000000000000000000011111000 #
1$
b00000000000000000000000011111000 &
b00000000000000000000000011111100 '
b00000000000000000000000011111000 (
#665000000
0!
0$
#670000000
1!
b00000000000000000000000011111100 #
1$
b00000000000000000000000011111100 &
b00000000000000000000000100000000 '
b00000000000000000000000011111100 (
#675000000
0!
0$
#680000000
1!
b00000000000000000000000100000000 #
1$
b00000000000000000000000100000000 &
b00000000000000000000000100000100 '
b00000000000000000000000100000000 (
#685000000
0!
0$
#690000000
1!
b00000000000000000000000100000100 #
1$
b00000000000000000000000100000100 &
b00000000000000000000000100001000 '
b00000000000000000000000100000100 (
#695000000
0!
0$
#700000000
1!
b00000000000000000000000100001000 #
1$
b00000000000000000000000100001000 &
b00000000000000000000000100001100 '
b00000000000000000000000100001000 (
#705000000
0!
0$
#710000000
1!
b00000000000000000000000100001100 #
1$
b00000000000000000000000100001100 &
b00000000000000000000000100010000 '
b00000000000000000000000100001100 (
#715000000
0!
0$
#720000000
1!
b00000000000000000000000100010000 #
1$
b00000000000000000000000100010000 &
b00000000000000000000000100010100 '
b00000000000000000000000100010000 (
#725000000
0!
0$
#730000000
1!
b00000000000000000000000100010100 #
1$
b00000000000000000000000100010100 &
b00000000000000000000000100011000 '
b00000000000000000000000100010100 (
#735000000
0!
0$
#740000000
1!
b00000000000000000000000100011000 #
1$
b00000000000000000000000100011000 &
b00000000000000000000000100011100 '
b00000000000000000000000100011000 (
#745000000
0!
0$
#750000000
1!
b00000000000000000000000100011100 #
1$
b00000000000000000000000100011100 &
b00000000000000000000000100100000 '
b00000000000000000000000100011100 (
#755000000
0!
0$
#760000000
1!
b00000000000000000000000100100000 #
1$
b00000000000000000000000100100000 &
b00000000000000000000000100100100 '
b00000000000000000000000100100000 (
#765000000
0!
0$
#770000000
1!
b00000000000000000000000100100100 #
1$
b00000000000000000000000100100100 &
b00000000000000000000000100101000 '
b00000000000000000000000100100100 (
#775000000
0!
0$
#780000000
1!
b00000000000000000000000100101000 #
1$
b00000000000000000000000100101000 &
b00000000000000000000000100101100 '
b00000000000000000000000100101000 (
#785000000
0!
0$
#790000000
1!
b00000000000000000000000100101100 #
1$
b00000000000000000000000100101100 &
b00000000000000000000000100110000 '
b00000000000000000000000100101100 (
#795000000
0!
0$
#800000000
1!
b00000000000000000000000100110000 #
1$
b00000000000000000000000100110000 &
b00000000000000000000000100110100 '
b00000000000000000000000100110000 (
#805000000
0!
0$
#810000000
1!
b00000000000000000000000100110100 #
1$
b00000000000000000000000100110100 &
b00000000000000000000000100111000 '
b00000000000000000000000100110100 (
#815000000
0!
0$
#820000000
1!
b00000000000000000000000100111000 #
1$
b00000000000000000000000100111000 &
b00000000000000000000000100111100 '
b00000000000000000000000100111000 (
#825000000
0!
0$
#830000000
1!
b00000000000000000000000100111100 #
1$
b00000000000000000000000100111100 &
b00000000000000000000000101000000 '
b00000000000000000000000100111100 (
#835000000
0!
0$
#840000000
1!
b00000000000000000000000101000000 #
1$
b00000000000000000000000101000000 &
b00000000000000000000000101000100 '
b00000000000000000000000101000000 (
#845000000
0!
0$
#850000000
1!
b00000000000000000000000101000100 #
1$
b00000000000000000000000101000100 &
b00000000000000000000000101001000 '
b00000000000000000000000101000100 (
#855000000
0!
0$
#860000000
1!
b00000000000000000000000101001000 #
1$
b00000000000000000000000101001000 &
b00000000000000000000000101001100 '
b00000000000000000000000101001000 (
#865000000
0!
0$
#870000000
1!
b00000000000000000000000101001100 #
1$
b00000000000000000000000101001100 &
b00000000000000000000000101010000 '
b00000000000000000000000101001100 (
#875000000
0!
0$
#880000000
1!
b00000000000000000000000101010000 #
1$
b00000000000000000000000101010000 &
b00000000000000000000000101010100 '
b00000000000000000000000101010000 (
#885000000
0!
0$
#890000000
1!
b00000000000000000000000101010100 #
1$
b00000000000000000000000101010100 &
b00000000000000000000000101011000 '
b00000000000000000000000101010100 (
#895000000
0!
0$
#900000000
1!
b00000000000000000000000101011000 #
1$
b00000000000000000000000101011000 &
b00000000000000000000000101011100 '
b00000000000000000000000101011000 (
#905000000
0!
0$
#910000000
1!
b00000000000000000000000101011100 #
1$
b00000000000000000000000101011100 &
b00000000000000000000000101100000 '
b00000000000000000000000101011100 (
#915000000
0!
0$
#920000000
1!
b00000000000000000000000101100000 #
1$
b00000000000000000000000101100000 &
b00000000000000000000000101100100 '
b00000000000000000000000101100000 (
#925000000
0!
0$
#930000000
1!
b00000000000000000000000101100100 #
1$
b00000000000000000000000101100100 &
b00000000000000000000000101101000 '
b00000000000000000000000101100100 (
#935000000
0!
0$
#940000000
1!
b00000000000000000000000101101000 #
1$
b00000000000000000000000101101000 &
b00000000000000000000000101101100 '
b00000000000000000000000101101000 (
#945000000
0!
0$
#950000000
1!
b00000000000000000000000101101100 #
1$
b00000000000000000000000101101100 &
b00000000000000000000000101110000 '
b00000000000000000000000101101100 (
#955000000
0!
0$
#960000000
1!
b00000000000000000000000101110000 #
1$
b00000000000000000000000101110000 &
b00000000000000000000000101110100 '
b00000000000000000000000101110000 (
#965000000
0!
0$
#970000000
1!
b00000000000000000000000101110100 #
1$
b00000000000000000000000101110100 &
b00000000000000000000000101111000 '
b00000000000000000000000101110100 (
#975000000
0!
0$
#980000000
1!
b00000000000000000000000101111000 #
1$
b00000000000000000000000101111000 &
b00000000000000000000000101111100 '
b00000000000000000000000101111000 (
#985000000
0!
0$
#990000000
1!
b00000000000000000000000101111100 #
1$
b00000000000000000000000101111100 &
b00000000000000000000000110000000 '
b00000000000000000000000101111100 (
#995000000
0!
0$
#1000000000
1!
b00000000000000000000000110000000 #
1$
b00000000000000000000000110000000 &
b00000000000000000000000110000100 '
b00000000000000000000000110000000 (
#1005000000
0!
0$
#1010000000
1!
b00000000000000000000000110000100 #
1$
b00000000000000000000000110000100 &
b00000000000000000000000110001000 '
b00000000000000000000000110000100 (
#1015000000
0!
0$
#1020000000
1!
b00000000000000000000000110001000 #
1$
b00000000000000000000000110001000 &
b00000000000000000000000110001100 '
b00000000000000000000000110001000 (
#1025000000
0!
0$
#1030000000
1!
b00000000000000000000000110001100 #
1$
b00000000000000000000000110001100 &
b00000000000000000000000110010000 '
b00000000000000000000000110001100 (
